gelf/__init__.py
gelf/formatter.py
gelf/handler.py
gelf-0.0.3.dist-info/METADATA
gelf-0.0.3.dist-info/WHEEL
gelf-0.0.3.dist-info/RECORD
