Metadata-Version: 2.4
Name: gelf
Version: 0.0.3
Summary: Library that provides classes for GELF logging!
Author-email: Sylvan Le Deunff <sylvan.ledeunff@gmail.com>
Maintainer-email: Sylvan Le Deunff <sylvan.ledeunff@gmail.com>
Keywords: gelf,logging
Classifier: Development Status :: 4 - Beta
Classifier: Programming Language :: Python
Requires-Python: >=3.8
